<PAMDataset>
  <PAMRasterBand band="1">
    <Histograms>
      <HistItem>
        <HistMin>-0.5522080659866333</HistMin>
        <HistMax>0.483467698097229</HistMax>
        <BucketCount>256</BucketCount>
        <IncludeOutOfRange>1</IncludeOutOfRange>
        <Approximate>0</Approximate>
        <HistCounts>1|0|1|1|2|0|3|2|2|1|2|5|4|6|20|15|42|36|59|77|65|108|109|109|136|161|153|136|161|157|168|214|203|168|209|243|252|245|248|245|278|279|328|361|373|352|350|337|338|360|371|377|360|383|380|328|371|327|364|323|307|291|274|280|234|220|237|221|215|238|216|211|220|201|188|213|194|184|142|147|141|133|114|121|97|121|90|89|87|79|82|54|59|78|98|125|145|191|210|236|227|255|265|254|280|266|304|346|350|326|330|297|285|306|281|307|349|362|408|496|591|685|750|913|1030|1121|1083|1091|1170|1241|1323|1608|1941|2449|3187|3903|3739|3984|4407|4996|6080|7665|9027|10300|11260|11797|12742|13857|14890|16305|17544|19382|21111|22670|24264|25317|25478|26311|26417|26368|25979|25485|25056|24294|23235|22342|21400|20116|19434|18694|17555|16682|15851|15133|14197|13615|12851|12017|11405|10686|10108|9752|9309|9046|8763|8157|8015|7504|7125|6761|6638|6193|5962|5780|5440|5234|4939|4635|4500|4314|4165|3733|3743|3340|3254|3063|2854|2617|2430|2328|2298|2201|2024|1939|1881|1816|1897|1819|1728|1669|1520|1612|1471|1507|1406|1400|1364|1276|1201|1165|1038|971|862|778|706|575|509|426|385|300|238|213|163|118|86|71|44|33|14|14|7|5|7|2|3|1</HistCounts>
      </HistItem>
    </Histograms>
    <Metadata>
      <MDI key="STATISTICS_COVARIANCES">0.01035820700312179</MDI>
      <MDI key="STATISTICS_EXCLUDEDVALUES"></MDI>
      <MDI key="STATISTICS_MAXIMUM">0.48346769809723</MDI>
      <MDI key="STATISTICS_MEAN">0.11828035202628</MDI>
      <MDI key="STATISTICS_MEDIAN">0,109812</MDI>
      <MDI key="STATISTICS_MINIMUM">-0.55220806598663</MDI>
      <MDI key="STATISTICS_SKIPFACTORX">1</MDI>
      <MDI key="STATISTICS_SKIPFACTORY">1</MDI>
      <MDI key="STATISTICS_STDDEV">0.10177527697394</MDI>
    </Metadata>
  </PAMRasterBand>
</PAMDataset>
